alu.v
module ALU (
    input [7:0] A, B,   // 8-bit inputs
    input [2:0] sel,    // Select signal for operation
    input clk, reset,   // Clock and reset signals
    output reg [7:0] Result // 8-bit result
);
    wire [7:0] sum, and_out, or_out, xor_out, left_shift, right_shift;
    reg [7:0] counter;

    // Submodules
    assign sum = A + B;               // Addition
    assign and_out = A & B;           // Bitwise AND
    assign or_out = A | B;            // Bitwise OR
    assign xor_out = A ^ B;           // Bitwise XOR
    assign left_shift = A << 1;       // Left Shift
    assign right_shift = A >> 1;      // Right Shift

    // Counter Logic
    always @(posedge clk or posedge reset) begin
        if (reset)
            counter <= 8'b0;
        else
            counter <= counter + 1;   // Increment Counter
    end

    // MUX8to1 to select the operation
    always @(*) begin
        case (sel)
            3'b000: Result = sum;          // Addition
            3'b001: Result = left_shift;   // Left Shift
            3'b010: Result = right_shift;  // Right Shift
            3'b011: Result = counter;      // Counter
            3'b100: Result = and_out;      // Bitwise AND
            3'b101: Result = or_out;       // Bitwise OR
            3'b110: Result = xor_out;      // Bitwise XOR
            default: Result = 8'b0;        // No Operation
        endcase
    end
endmodule

alu_tb.v
module tb_ALU;
    reg [7:0] A, B;         // Inputs
    reg [2:0] sel;          // Select signal
    reg clk, reset;         // Clock and reset
    wire [7:0] Result;      // Output

    // Instantiate the ALU
    ALU uut (
        .A(A),
        .B(B),
        .sel(sel),
        .clk(clk),
        .reset(reset),
        .Result(Result)
    );

    // Clock Generation
    always #5 clk = ~clk;

    initial begin
        // Dump waveform for GTKWave
        $dumpfile("alu_wave.vcd");
        $dumpvars(0, tb_ALU);

        // Initialize inputs
        clk = 0; reset = 1;
        A = 8'h0; B = 8'h0; sel = 3'b000;
        #10 reset = 0;

        // Test Addition
        A = 8'h05; B = 8'h03; sel = 3'b000; #10;

        // Test Left Shift
        sel = 3'b001; #10;

        // Test Right Shift
        sel = 3'b010; #10;

        // Test Counter
        sel = 3'b011; #50;

        // Test Bitwise AND
        sel = 3'b100; #10;

        // Test Bitwise OR
        sel = 3'b101; #10;

        // Test Bitwise XOR
        sel = 3'b110; #10;

        // End Simulation
        $finish;
    end
endmodule

alu_wave.vcd
$date
	Wed Dec 11 19:50:43 2024
$end
$version
	Icarus Verilog
$end
$timescale
	1s
$end
$scope module tb_ALU $end
$var wire 8 ! Result [7:0] $end
$var reg 8 " A [7:0] $end
$var reg 8 # B [7:0] $end
$var reg 1 $ clk $end
$var reg 1 % reset $end
$var reg 3 & sel [2:0] $end
$scope module uut $end
$var wire 8 ' A [7:0] $end
$var wire 8 ( B [7:0] $end
$var wire 8 ) and_out [7:0] $end
$var wire 1 $ clk $end
$var wire 8 * or_out [7:0] $end
$var wire 1 % reset $end
$var wire 3 + sel [2:0] $end
$var wire 8 , xor_out [7:0] $end
$var wire 8 - sum [7:0] $end
$var wire 8 . right_shift [7:0] $end
$var wire 8 / left_shift [7:0] $end
$var reg 8 0 Result [7:0] $end
$var reg 8 1 counter [7:0] $end
$upscope $end
$upscope $end
$enddefinitions $end
#0
$dumpvars
b0 1
b0 0
b0 /
b0 .
b0 -
b0 ,
b0 +
b0 *
b0 )
b0 (
b0 '
b0 &
1%
0$
b0 #
b0 "
b0 !
$end
#5
1$
#10
b1 )
b111 *
b110 ,
b1000 !
b1000 0
b1010 /
b10 .
0$
b11 #
b11 (
b1000 -
b101 "
b101 '
0%
#15
b1 1
1$
#20
b1010 !
b1010 0
0$
b1 &
b1 +
#25
b10 1
1$
#30
b10 !
b10 0
0$
b10 &
b10 +
#35
b11 1
1$
#40
b11 !
b11 0
0$
b11 &
b11 +
#45
b100 !
b100 0
b100 1
1$
#50
0$
#55
b101 !
b101 0
b101 1
1$
#60
0$
#65
b110 !
b110 0
b110 1
1$
#70
0$
#75
b111 !
b111 0
b111 1
1$
#80
0$
#85
b1000 !
b1000 0
b1000 1
1$
#90
b1 !
b1 0
0$
b100 &
b100 +
#95
b1001 1
1$
#100
b111 !
b111 0
0$
b101 &
b101 +
#105
b1010 1
1$
#110
b110 !
b110 0
0$
b110 &
b110 +
#115
b1011 1
1$
