counter.v
module counter (
    input [7:0] Data,    // 8-bit data input for load operation
    input enable,         // Enable signal (count or hold)
    input load,           // Load signal (load Data into counter)
    input clk,            // Clock signal
    input reset,          // Asynchronous reset
    output reg [7:0] Q    // 8-bit output counter value
);

    always @(posedge clk or posedge reset) begin
        if (reset) begin
            // Reset the counter to 0 when reset is high
            Q <= 8'b00000000;
        end else if (load) begin
            // Load new value into counter when load is high
            Q <= Data;
        end else if (enable) begin
            // Increment the counter when enable is high
            Q <= Q + 1;
        end
    end

endmodule

counter_tb.v
module tb_counter;
    reg [7:0] Data;      // 8-bit data input for load operation
    reg enable;          // Enable signal
    reg load;            // Load signal
    reg clk;             // Clock signal
    reg reset;           // Reset signal
    wire [7:0] Q;        // 8-bit output of the counter

    // Instantiate the counter module
    counter uut (
        .Data(Data),
        .enable(enable),
        .load(load),
        .clk(clk),
        .reset(reset),
        .Q(Q)
    );

    // Clock generation
    always begin
        #5 clk = ~clk;  // Toggle clock every 5 time units
    end

    initial begin
        // Initialize signals
        clk = 0;
        reset = 0;
        enable = 0;
        load = 0;
        Data = 8'b00000000;

        // Dump waveform for GTKWave
        $dumpfile("counter_wave.vcd");
        $dumpvars(0, tb_counter);

        // Test case 1: Reset the counter
        reset = 1;
        #10;
        reset = 0;
        #10;

        // Test case 2: Load a value into the counter (0x55)
        load = 1;
        Data = 8'b01010101; // Load 0x55 into the counter
        #10;
        load = 0;
        #10;

        // Test case 3: Enable the counter to increment
        enable = 1;
        #50;  // Let the counter run for 50 time units

        // Test case 4: Disable enable and hold the value
        enable = 0;
        #10;

        // Test case 5: Load a new value into the counter (0xFF)
        load = 1;
        Data = 8'b11111111; // Load 0xFF into the counter
        #10;

        $finish;
    end
endmodule

counter_wave.vcd
$date
	Wed Dec 11 19:31:39 2024
$end
$version
	Icarus Verilog
$end
$timescale
	1s
$end
$scope module tb_counter $end
$var wire 8 ! Q [7:0] $end
$var reg 8 " Data [7:0] $end
$var reg 1 # clk $end
$var reg 1 $ enable $end
$var reg 1 % load $end
$var reg 1 & reset $end
$scope module uut $end
$var wire 8 ' Data [7:0] $end
$var wire 1 # clk $end
$var wire 1 $ enable $end
$var wire 1 % load $end
$var wire 1 & reset $end
$var reg 8 ( Q [7:0] $end
$upscope $end
$upscope $end
$enddefinitions $end
#0
$dumpvars
b0 (
b0 '
1&
0%
0$
0#
b0 "
b0 !
$end
#5
1#
#10
0#
0&
#15
1#
#20
0#
b1010101 "
b1010101 '
1%
#25
b1010101 !
b1010101 (
1#
#30
0#
0%
#35
1#
#40
0#
1$
#45
b1010110 !
b1010110 (
1#
#50
0#
#55
b1010111 !
b1010111 (
1#
#60
0#
#65
b1011000 !
b1011000 (
1#
#70
0#
#75
b1011001 !
b1011001 (
1#
#80
0#
#85
b1011010 !
b1011010 (
1#
#90
0#
0$
#95
1#
#100
0#
b11111111 "
b11111111 '
1%
#105
b11111111 !
b11111111 (
1#
