decoder3to8.v
module Decoder3to8 (
    input [2:0] A,  // 3-bit input
    output reg [7:0] Y  // 8-bit output
);
    always @(*) begin
        case (A)
            3'b000: Y = 8'b00000001;
            3'b001: Y = 8'b00000010;
            3'b010: Y = 8'b00000100;
            3'b011: Y = 8'b00001000;
            3'b100: Y = 8'b00010000;
            3'b101: Y = 8'b00100000;
            3'b110: Y = 8'b01000000;
            3'b111: Y = 8'b10000000;
            default: Y = 8'b00000000;  // Default case
        endcase
    end
endmodule

decoder3to8_tb.v
module tb_Decoder3to8;
    reg [2:0] A;  // 3-bit input
    wire [7:0] Y;  // 8-bit output
    
    // Instantiate the Decoder3to8
    Decoder3to8 uut (
        .A(A),
        .Y(Y)
    );
    
    initial begin
        // Test all combinations of A
        A = 3'b000; #10;
        A = 3'b001; #10;
        A = 3'b010; #10;
        A = 3'b011; #10;
        A = 3'b100; #10;
        A = 3'b101; #10;
        A = 3'b110; #10;
        A = 3'b111; #10;
        
        // End simulation
        $finish;
    end
    
    initial begin
        // Dump waveforms for GTKWave
        $dumpfile("decoder3to8.vcd");
        $dumpvars(0, tb_Decoder3to8);
    end
endmodule

decoder3to8.vcd
$date
	Wed Dec 11 16:57:01 2024
$end
$version
	Icarus Verilog
$end
$timescale
	1s
$end
$scope module tb_Decoder3to8 $end
$var wire 8 ! Y [7:0] $end
$var reg 3 " A [2:0] $end
$scope module uut $end
$var wire 3 # A [2:0] $end
$var reg 8 $ Y [7:0] $end
$upscope $end
$upscope $end
$enddefinitions $end
#0
$dumpvars
b1 $
b0 #
b0 "
b1 !
$end
#10
b10 !
b10 $
b1 "
b1 #
#20
b100 !
b100 $
b10 "
b10 #
#30
b1000 !
b1000 $
b11 "
b11 #
#40
b10000 !
b10000 $
b100 "
b100 #
#50
b100000 !
b100000 $
b101 "
b101 #
#60
b1000000 !
b1000000 $
b110 "
b110 #
#70
b10000000 !
b10000000 $
b111 "
b111 #
