mux8to1.v
module MUX8to1_4bit (
    input [3:0] D0, D1, D2, D3, D4, D5, D6, D7,  // 8 data inputs
    input [2:0] S,                            // 3-bit select input
    output reg [3:0] Y                        // 4-bit output
);
    always @(*) begin
        case(S)
            3'b000: Y = D0;
            3'b001: Y = D1;
            3'b010: Y = D2;
            3'b011: Y = D3;
            3'b100: Y = D4;
            3'b101: Y = D5;
            3'b110: Y = D6;
            3'b111: Y = D7;
            default: Y = 4'b0000;
        endcase
    end
endmodule

mux8to1_tb.v
module tb_MUX8to1_4bit;
    reg [3:0] D0, D1, D2, D3, D4, D5, D6, D7;  // Data inputs
    reg [2:0] S;                                 // Select input
    wire [3:0] Y;                                // Output
    
    // Instantiate the MUX8to1_4bit
    MUX8to1_4bit uut (
        .D0(D0), .D1(D1), .D2(D2), .D3(D3), .D4(D4), .D5(D5), .D6(D6), .D7(D7),
        .S(S), .Y(Y)
    );
    
    initial begin
    $dumpfile("mux8to1_4bit.vcd");
    $dumpvars(0, tb_MUX8to1_4bit);
end

    initial begin
        // Initialize Inputs
        D0 = 4'b0001; D1 = 4'b0010; D2 = 4'b0011; D3 = 4'b0100;
        D4 = 4'b0101; D5 = 4'b0110; D6 = 4'b0111; D7 = 4'b1000;
        
        // Test all select combinations
        for (S = 0; S < 8; S = S + 1) begin
            #10;
            $display("S = %b, Y = %b", S, Y);
        end
    end
endmodule

mux8to1_4bit.vcd
$date
	Wed Dec 11 16:28:37 2024
$end
$version
	Icarus Verilog
$end
$timescale
	1s
$end
$scope module tb_MUX8to1_4bit $end
$var wire 4 ! Y [3:0] $end
$var reg 4 " D0 [3:0] $end
$var reg 4 # D1 [3:0] $end
$var reg 4 $ D2 [3:0] $end
$var reg 4 % D3 [3:0] $end
$var reg 4 & D4 [3:0] $end
$var reg 4 ' D5 [3:0] $end
$var reg 4 ( D6 [3:0] $end
$var reg 4 ) D7 [3:0] $end
$var reg 3 * S [2:0] $end
$scope module uut $end
$var wire 4 + D0 [3:0] $end
$var wire 4 , D1 [3:0] $end
$var wire 4 - D2 [3:0] $end
$var wire 4 . D3 [3:0] $end
$var wire 4 / D4 [3:0] $end
$var wire 4 0 D5 [3:0] $end
$var wire 4 1 D6 [3:0] $end
$var wire 4 2 D7 [3:0] $end
$var wire 3 3 S [2:0] $end
$var reg 4 4 Y [3:0] $end
$upscope $end
$upscope $end
$enddefinitions $end
#0
$dumpvars
b1 4
b0 3
b1000 2
b111 1
b110 0
b101 /
b100 .
b11 -
b10 ,
b1 +
b0 *
b1000 )
b111 (
b110 '
b101 &
b100 %
b11 $
b10 #
b1 "
b1 !
$end
#10
b10 !
b10 4
b1 *
b1 3
#20
b11 !
b11 4
b10 *
b10 3
#30
b100 !
b100 4
b11 *
b11 3
#40
b101 !
b101 4
b100 *
b100 3
#50
b110 !
b110 4
b101 *
b101 3
#60
b111 !
b111 4
b110 *
b110 3
#70
b1000 !
b1000 4
b111 *
b111 3
#80
b1 !
b1 4
b0 *
b0 3
#90
b10 !
b10 4
b1 *
b1 3
#100
b11 !
b11 4
b10 *
b10 3
#110
b100 !
b100 4
b11 *
b11 3
#120
b101 !
b101 4
b100 *
b100 3
#130
b110 !
b110 4
b101 *
b101 3
#140
b111 !
b111 4
b110 *
b110 3
#150
b1000 !
b1000 4
b111 *
b111 3
#160
b1 !
b1 4
b0 *
b0 3
#170
b10 !
b10 4
b1 *
b1 3
#180
b11 !
b11 4
b10 *
b10 3
#190
b100 !
b100 4
b11 *
b11 3
#200
b101 !
b101 4
b100 *
b100 3
#210
b110 !
b110 4
b101 *
b101 3
#220
b111 !
b111 4
b110 *
b110 3
#230
b1000 !
b1000 4
b111 *
b111 3
#240
b1 !
b1 4
b0 *
b0 3
#250
b10 !
b10 4
b1 *
b1 3
#260
b11 !
b11 4
b10 *
b10 3
#270
b100 !
b100 4
b11 *
b11 3
#280
b101 !
b101 4
b100 *
b100 3
#290
b110 !
b110 4
b101 *
b101 3
#300
b111 !
b111 4
b110 *
b110 3
#310
b1000 !
b1000 4
b111 *
b111 3
#320
b1 !
b1 4
b0 *
b0 3
#330
b10 !
b10 4
b1 *
b1 3
#340
b11 !
b11 4
b10 *
b10 3
#350
b100 !
b100 4
b11 *
b11 3
#360
b101 !
b101 4
b100 *
b100 3
#370
b110 !
b110 4
b101 *
b101 3
#380
b111 !
b111 4
b110 *
b110 3
#390
b1000 !
b1000 4
b111 *
b111 3
#400
b1 !
b1 4
b0 *
b0 3
#410
b10 !
b10 4
b1 *
b1 3
#420
b11 !
b11 4
b10 *
b10 3
#430
b100 !
b100 4
b11 *
b11 3
#440
b101 !
b101 4
b100 *
b100 3
#450
b110 !
b110 4
b101 *
b101 3
#460
b111 !
b111 4
b110 *
b110 3
#470
b1000 !
b1000 4
b111 *
b111 3
#480
b1 !
b1 4
b0 *
b0 3
#490
b10 !
b10 4
b1 *
b1 3
#500
b11 !
b11 4
b10 *
b10 3
#510
b100 !
b100 4
b11 *
b11 3
#520
b101 !
b101 4
b100 *
b100 3
#530
b110 !
b110 4
b101 *
b101 3
#540
b111 !
b111 4
b110 *
b110 3
#550
b1000 !
b1000 4
b111 *
b111 3
#560
b1 !
b1 4
b0 *
b0 3
#570
b10 !
b10 4
b1 *
b1 3
#580
b11 !
b11 4
b10 *
b10 3
#590
b100 !
b100 4
b11 *
b11 3
#600
b101 !
b101 4
b100 *
b100 3
#610
b110 !
b110 4
b101 *
b101 3
#620
b111 !
b111 4
b110 *
b110 3
#630
b1000 !
b1000 4
b111 *
b111 3
#640
b1 !
b1 4
b0 *
b0 3
#650
b10 !
b10 4
b1 *
b1 3
#660
b11 !
b11 4
b10 *
b10 3
#670
b100 !
b100 4
b11 *
b11 3
#680
b101 !
b101 4
b100 *
b100 3
#690
b110 !
b110 4
b101 *
b101 3
#700
b111 !
b111 4
b110 *
b110 3
#710
b1000 !
b1000 4
b111 *
b111 3
#720
b1 !
b1 4
b0 *
b0 3
#730
b10 !
b10 4
b1 *
b1 3
#740
b11 !
b11 4
b10 *
b10 3
#750
b100 !
b100 4
b11 *
b11 3
#760
b101 !
b101 4
b100 *
b100 3
#770
b110 !
b110 4
b101 *
b101 3
#780
b111 !
b111 4
b110 *
b110 3
#790
b1000 !
b1000 4
b111 *
b111 3
#800
b1 !
b1 4
b0 *
b0 3
#810
b10 !
b10 4
b1 *
b1 3
#820
b11 !
b11 4
b10 *
b10 3
#830
b100 !
b100 4
b11 *
b11 3
#840
b101 !
b101 4
b100 *
b100 3
#850
b110 !
b110 4
b101 *
b101 3
#860
b111 !
b111 4
b110 *
b110 3
#870
b1000 !
b1000 4
b111 *
b111 3
#880
b1 !
b1 4
b0 *
b0 3
#890
b10 !
b10 4
b1 *
b1 3
#900
b11 !
b11 4
b10 *
b10 3
#910
b100 !
b100 4
b11 *
b11 3
#920
b101 !
b101 4
b100 *
b100 3
#930
b110 !
b110 4
b101 *
b101 3
#940
b111 !
b111 4
b110 *
b110 3
#950
b1000 !
b1000 4
b111 *
b111 3
#960
b1 !
b1 4
b0 *
b0 3
#970
b10 !
b10 4
b1 *
b1 3
#980
b11 !
b11 4
b10 *
b10 3
#990
b100 !
b100 4
b11 *
b11 3
#1000
b101 !
b101 4
b100 *
b100 3
#1010
b110 !
b110 4
b101 *
b101 3
#1020
b111 !
b111 4
b110 *
b110 3
#1030
b1000 !
b1000 4
b111 *
b111 3
#1040
b1 !
b1 4
b0 *
b0 3
#1050
b10 !
b10 4
b1 *
b1 3
#1060
b11 !
b11 4
b10 *
b10 3
#1070
b100 !
b100 4
b11 *
b11 3
#1080
b101 !
b101 4
b100 *
b100 3
#1090
b110 !
b110 4
b101 *
b101 3
#1100
b111 !
b111 4
b110 *
b110 3
#1110
b1000 !
b1000 4
b111 *
b111 3
#1120
b1 !
b1 4
b0 *
b0 3
#1130
b10 !
b10 4
b1 *
b1 3
#1140
b11 !
b11 4
b10 *
b10 3
#1150
b100 !
b100 4
b11 *
b11 3
#1160
b101 !
b101 4
b100 *
b100 3
#1170
b110 !
b110 4
b101 *
b101 3
#1180
b111 !
b111 4
b110 *
b110 3
#1190
b1000 !
b1000 4
b111 *
b111 3
#1200
b1 !
b1 4
b0 *
b0 3
#1210
b10 !
b10 4
b1 *
b1 3
#1220
b11 !
b11 4
b10 *
b10 3
#1230
b100 !
b100 4
b11 *
b11 3
#1240
b101 !
b101 4
b100 *
b100 3
#1250
b110 !
b110 4
b101 *
b101 3
#1260
b111 !
b111 4
b110 *
b110 3
#1270
b1000 !
b1000 4
b111 *
b111 3
#1280
b1 !
b1 4
b0 *
b0 3
#1290
b10 !
b10 4
b1 *
b1 3
#1300
b11 !
b11 4
b10 *
b10 3
#1310
b100 !
b100 4
b11 *
b11 3
#1320
b101 !
b101 4
b100 *
b100 3
#1330
b110 !
b110 4
b101 *
b101 3
#1340
b111 !
b111 4
b110 *
b110 3
#1350
b1000 !
b1000 4
b111 *
b111 3
#1360
b1 !
b1 4
b0 *
b0 3
#1370
b10 !
b10 4
b1 *
b1 3
#1380
b11 !
b11 4
b10 *
b10 3
#1390
b100 !
b100 4
b11 *
b11 3
#1400
b101 !
b101 4
b100 *
b100 3
#1410
b110 !
b110 4
b101 *
b101 3
#1420
b111 !
b111 4
b110 *
b110 3
#1430
b1000 !
b1000 4
b111 *
b111 3
#1440
b1 !
b1 4
b0 *
b0 3
#1450
b10 !
b10 4
b1 *
b1 3
#1460
b11 !
b11 4
b10 *
b10 3
#1470
b100 !
b100 4
b11 *
b11 3
#1480
b101 !
b101 4
b100 *
b100 3
#1490
b110 !
b110 4
b101 *
b101 3
#1500
b111 !
b111 4
b110 *
b110 3
#1510
b1000 !
b1000 4
b111 *
b111 3
#1520
b1 !
b1 4
b0 *
b0 3
#1530
b10 !
b10 4
b1 *
b1 3
#1540
b11 !
b11 4
b10 *
b10 3
#1550
b100 !
b100 4
b11 *
b11 3
#1560
b101 !
b101 4
b100 *
b100 3
#1570
b110 !
b110 4
b101 *
b101 3
#1580
b111 !
b111 4
b110 *
b110 3
#1590
b1000 !
b1000 4
b111 *
b111 3
#1600
b1 !
b1 4
b0 *
b0 3
#1610
b10 !
b10 4
b1 *
b1 3
#1620
b11 !
b11 4
b10 *
b10 3
#1630
b100 !
b100 4
b11 *
b11 3
#1640
b101 !
b101 4
b100 *
b100 3
#1650
b110 !
b110 4
b101 *
b101 3
#1660
b111 !
b111 4
b110 *
b110 3
#1670
b1000 !
b1000 4
b111 *
b111 3
#1680
b1 !
b1 4
b0 *
b0 3
#1690
b10 !
b10 4
b1 *
b1 3
#1700
b11 !
b11 4
b10 *
b10 3
#1710
b100 !
b100 4
b11 *
b11 3
#1720
b101 !
b101 4
b100 *
b100 3
#1730
b110 !
b110 4
b101 *
b101 3
#1740
b111 !
b111 4
b110 *
b110 3
#1750
b1000 !
b1000 4
b111 *
b111 3
#1760
b1 !
b1 4
b0 *
b0 3
#1770
b10 !
b10 4
b1 *
b1 3
#1780
b11 !
b11 4
b10 *
b10 3
#1790
b100 !
b100 4
b11 *
b11 3
#1800
b101 !
b101 4
b100 *
b100 3
#1810
b110 !
b110 4
b101 *
b101 3
#1820
b111 !
b111 4
b110 *
b110 3
#1830
b1000 !
b1000 4
b111 *
b111 3
#1840
b1 !
b1 4
b0 *
b0 3
#1850
b10 !
b10 4
b1 *
b1 3
#1860
b11 !
b11 4
b10 *
b10 3
#1870
b100 !
b100 4
b11 *
b11 3
#1880
b101 !
b101 4
b100 *
b100 3
#1890
b110 !
b110 4
b101 *
b101 3
#1900
b111 !
b111 4
b110 *
b110 3
#1910
b1000 !
b1000 4
b111 *
b111 3
#1920
b1 !
b1 4
b0 *
b0 3
#1930
b10 !
b10 4
b1 *
b1 3
#1940
b11 !
b11 4
b10 *
b10 3
#1950
b100 !
b100 4
b11 *
b11 3
#1960
b101 !
b101 4
b100 *
b100 3
#1970
b110 !
b110 4
b101 *
b101 3
#1980
b111 !
b111 4
b110 *
b110 3
#1990
b1000 !
b1000 4
b111 *
b111 3
#2000
b1 !
b1 4
b0 *
b0 3
#2010
b10 !
b10 4
b1 *
b1 3
#2020
b11 !
b11 4
b10 *
b10 3
#2030
b100 !
b100 4
b11 *
b11 3
#2040
b101 !
b101 4
b100 *
b100 3
#2050
b110 !
b110 4
b101 *
b101 3
#2060
b111 !
b111 4
b110 *
b110 3
#2070
b1000 !
b1000 4
b111 *
b111 3
#2080
b1 !
b1 4
b0 *
b0 3
#2090
b10 !
b10 4
b1 *
b1 3
#2100
b11 !
b11 4
b10 *
b10 3
#2110
b100 !
b100 4
b11 *
b11 3
#2120
b101 !
b101 4
b100 *
b100 3
#2130
b110 !
b110 4
b101 *
b101 3
#2140
b111 !
b111 4
b110 *
b110 3
#2150
b1000 !
b1000 4
b111 *
b111 3
#2160
b1 !
b1 4
b0 *
b0 3
#2170
b10 !
b10 4
b1 *
b1 3
#2180
b11 !
b11 4
b10 *
b10 3
#2190
b100 !
b100 4
b11 *
b11 3
#2200
b101 !
b101 4
b100 *
b100 3
#2210
b110 !
b110 4
b101 *
b101 3
#2220
b111 !
b111 4
b110 *
b110 3
#2230
b1000 !
b1000 4
b111 *
b111 3
#2240
b1 !
b1 4
b0 *
b0 3
#2250
b10 !
b10 4
b1 *
b1 3
#2260
b11 !
b11 4
b10 *
b10 3
#2270
b100 !
b100 4
b11 *
b11 3
#2280
b101 !
b101 4
b100 *
b100 3
#2290
b110 !
b110 4
b101 *
b101 3
#2300
b111 !
b111 4
b110 *
b110 3
#2310
b1000 !
b1000 4
b111 *
b111 3
#2320
b1 !
b1 4
b0 *
b0 3
#2330
b10 !
b10 4
b1 *
b1 3
#2340
b11 !
b11 4
b10 *
b10 3
#2350
b100 !
b100 4
b11 *
b11 3
#2360
b101 !
b101 4
b100 *
b100 3
#2370
b110 !
b110 4
b101 *
b101 3
#2380
b111 !
b111 4
b110 *
b110 3
#2390
b1000 !
b1000 4
b111 *
b111 3
#2400
b1 !
b1 4
b0 *
b0 3
#2410
b10 !
b10 4
b1 *
b1 3
#2420
b11 !
b11 4
b10 *
b10 3
#2430
b100 !
b100 4
b11 *
b11 3
#2440
b101 !
b101 4
b100 *
b100 3
#2450
b110 !
b110 4
b101 *
b101 3
#2460
b111 !
b111 4
b110 *
b110 3
#2470
b1000 !
b1000 4
b111 *
b111 3
#2480
b1 !
b1 4
b0 *
b0 3
#2490
b10 !
b10 4
b1 *
b1 3
#2500
b11 !
b11 4
b10 *
b10 3
#2510
b100 !
b100 4
b11 *
b11 3
#2520
b101 !
b101 4
b100 *
b100 3
#2530
b110 !
b110 4
b101 *
b101 3
#2540
b111 !
b111 4
b110 *
b110 3
#2550
b1000 !
b1000 4
b111 *
b111 3
#2560
b1 !
b1 4
b0 *
b0 3
#2570
b10 !
b10 4
b1 *
b1 3
#2580
b11 !
b11 4
b10 *
b10 3
#2590
b100 !
b100 4
b11 *
b11 3
#2600
b101 !
b101 4
b100 *
b100 3
#2610
b110 !
b110 4
b101 *
b101 3
#2620
b111 !
b111 4
b110 *
b110 3
#2630
b1000 !
b1000 4
b111 *
b111 3
#2640
b1 !
b1 4
b0 *
b0 3
#2650
b10 !
b10 4
b1 *
b1 3
#2660
b11 !
b11 4
b10 *
b10 3
#2670
b100 !
b100 4
b11 *
b11 3
#2680
b101 !
b101 4
b100 *
b100 3
#2690
b110 !
b110 4
b101 *
b101 3
#2700
b111 !
b111 4
b110 *
b110 3
#2710
b1000 !
b1000 4
b111 *
b111 3
#2720
b1 !
b1 4
b0 *
b0 3
#2730
b10 !
b10 4
b1 *
b1 3
#2740
b11 !
b11 4
b10 *
b10 3
#2750
b100 !
b100 4
b11 *
b11 3
#2760
b101 !
b101 4
b100 *
b100 3
#2770
b110 !
b110 4
b101 *
b101 3
#2780
b111 !
b111 4
b110 *
b110 3
#2790
b1000 !
b1000 4
b111 *
b111 3
#2800
b1 !
b1 4
b0 *
b0 3
#2810
b10 !
b10 4
b1 *
b1 3
#2820
b11 !
b11 4
b10 *
b10 3
#2830
b100 !
b100 4
b11 *
b11 3
#2840
b101 !
b101 4
b100 *
b100 3
#2850
b110 !
b110 4
b101 *
b101 3
#2860
b111 !
b111 4
b110 *
b110 3
#2870
b1000 !
b1000 4
b111 *
b111 3
#2880
b1 !
b1 4
b0 *
b0 3
#2890
b10 !
b10 4
b1 *
b1 3
#2900
b11 !
b11 4
b10 *
b10 3
#2910
b100 !
b100 4
b11 *
b11 3
#2920
b101 !
b101 4
b100 *
b100 3
#2930
b110 !
b110 4
b101 *
b101 3
#2940
b111 !
b111 4
b110 *
b110 3
#2950
b1000 !
b1000 4
b111 *
b111 3
#2960
b1 !
b1 4
b0 *
b0 3
#2970
b10 !
b10 4
b1 *
b1 3
#2980
b11 !
b11 4
b10 *
b10 3
#2990
b100 !
b100 4
b11 *
b11 3
#3000
b101 !
b101 4
b100 *
b100 3
#3010
b110 !
b110 4
b101 *
b101 3
#3020
b111 !
b111 4
b110 *
b110 3
#3030
b1000 !
b1000 4
b111 *
b111 3
#3040
b1 !
b1 4
b0 *
b0 3
#3050
b10 !
b10 4
b1 *
b1 3
#3060
b11 !
b11 4
b10 *
b10 3
#3070
b100 !
b100 4
b11 *
b11 3
#3080
b101 !
b101 4
b100 *
b100 3
#3090
b110 !
b110 4
b101 *
b101 3
#3100
b111 !
b111 4
b110 *
b110 3
#3110
b1000 !
b1000 4
b111 *
b111 3
#3120
b1 !
b1 4
b0 *
b0 3
#3130
b10 !
b10 4
b1 *
b1 3
#3140
b11 !
b11 4
b10 *
b10 3
#3150
b100 !
b100 4
b11 *
b11 3
#3160
b101 !
b101 4
b100 *
b100 3
#3170
b110 !
b110 4
b101 *
b101 3
#3180
b111 !
b111 4
b110 *
b110 3
#3190
b1000 !
b1000 4
b111 *
b111 3
#3200
b1 !
b1 4
b0 *
b0 3
#3210
b10 !
b10 4
b1 *
b1 3
#3220
b11 !
b11 4
b10 *
b10 3
#3230
b100 !
b100 4
b11 *
b11 3
#3240
b101 !
b101 4
b100 *
b100 3
#3250
b110 !
b110 4
b101 *
b101 3
#3260
b111 !
b111 4
b110 *
b110 3
#3270
b1000 !
b1000 4
b111 *
b111 3
#3280
b1 !
b1 4
b0 *
b0 3
#3290
b10 !
b10 4
b1 *
b1 3
#3300
b11 !
b11 4
b10 *
b10 3
#3310
b100 !
b100 4
b11 *
b11 3
#3320
b101 !
b101 4
b100 *
b100 3
#3330
b110 !
b110 4
b101 *
b101 3
#3340
b111 !
b111 4
b110 *
b110 3
#3350
b1000 !
b1000 4
b111 *
b111 3
#3360
b1 !
b1 4
b0 *
b0 3
#3370
b10 !
b10 4
b1 *
b1 3
#3380
b11 !
b11 4
b10 *
b10 3
#3390
b100 !
b100 4
b11 *
b11 3
#3400
b101 !
b101 4
b100 *
b100 3
#3410
b110 !
b110 4
b101 *
b101 3
#3420
b111 !
b111 4
b110 *
b110 3
#3430
b1000 !
b1000 4
b111 *
b111 3
#3440
b1 !
b1 4
b0 *
b0 3
#3450
b10 !
b10 4
b1 *
b1 3
#3460
b11 !
b11 4
b10 *
b10 3
#3470
b100 !
b100 4
b11 *
b11 3
#3480
b101 !
b101 4
b100 *
b100 3
#3490
b110 !
b110 4
b101 *
b101 3
#3500
b111 !
b111 4
b110 *
b110 3
#3510
b1000 !
b1000 4
b111 *
b111 3
#3520
b1 !
b1 4
b0 *
b0 3
#3530
b10 !
b10 4
b1 *
b1 3
#3540
b11 !
b11 4
b10 *
b10 3
#3550
b100 !
b100 4
b11 *
b11 3
#3560
b101 !
b101 4
b100 *
b100 3
#3570
b110 !
b110 4
b101 *
b101 3
#3580
b111 !
b111 4
b110 *
b110 3
#3590
b1000 !
b1000 4
b111 *
b111 3
#3600
b1 !
b1 4
b0 *
b0 3
#3610
b10 !
b10 4
b1 *
b1 3
#3620
b11 !
b11 4
b10 *
b10 3
#3630
b100 !
b100 4
b11 *
b11 3
#3640
b101 !
b101 4
b100 *
b100 3
#3650
b110 !
b110 4
b101 *
b101 3
#3660
b111 !
b111 4
b110 *
b110 3
#3670
b1000 !
b1000 4
b111 *
b111 3
#3680
b1 !
b1 4
b0 *
b0 3
#3690
b10 !
b10 4
b1 *
b1 3
#3700
b11 !
b11 4
b10 *
b10 3
#3710
b100 !
b100 4
b11 *
b11 3
#3720
b101 !
b101 4
b100 *
b100 3
#3730
b110 !
b110 4
b101 *
b101 3
#3740
b111 !
b111 4
b110 *
b110 3
#3750
b1000 !
b1000 4
b111 *
b111 3
#3760
b1 !
b1 4
b0 *
b0 3
#3770
b10 !
b10 4
b1 *
b1 3
#3780
b11 !
b11 4
b10 *
b10 3
#3790
b100 !
b100 4
b11 *
b11 3
#3800
b101 !
b101 4
b100 *
b100 3
#3810
b110 !
b110 4
b101 *
b101 3
#3820
b111 !
b111 4
b110 *
b110 3
#3830
b1000 !
b1000 4
b111 *
b111 3
#3840
b1 !
b1 4
b0 *
b0 3
#3850
b10 !
b10 4
b1 *
b1 3
#3860
b11 !
b11 4
b10 *
b10 3
#3870
b100 !
b100 4
b11 *
b11 3
#3880
b101 !
b101 4
b100 *
b100 3
#3890
b110 !
b110 4
b101 *
b101 3
#3900
b111 !
b111 4
b110 *
b110 3
#3910
b1000 !
b1000 4
b111 *
b111 3
#3920
b1 !
b1 4
b0 *
b0 3
#3930
b10 !
b10 4
b1 *
b1 3
#3940
b11 !
b11 4
b10 *
b10 3
#3950
b100 !
b100 4
b11 *
b11 3
#3960
b101 !
b101 4
b100 *
b100 3
#3970
b110 !
b110 4
b101 *
b101 3
#3980
b111 !
b111 4
b110 *
b110 3
#3990
b1000 !
b1000 4
b111 *
b111 3
#4000
b1 !
b1 4
b0 *
b0 3
#4010
b10 !
b10 4
b1 *
b1 3
#4020
b11 !
b11 4
b10 *
b10 3
#4030
b100 !
b100 4
b11 *
b11 3
#4040
b101 !
b101 4
b100 *
b100 3
#4050
b110 !
b110 4
b101 *
b101 3
#4060
b111 !
b111 4
b110 *
b110 3
#4070
b1000 !
b1000 4
b111 *
b111 3
#4080
b1 !
b1 4
b0 *
b0 3
#4090
b10 !
b10 4
b1 *
b1 3
#4100
b11 !
b11 4
b10 *
b10 3
#4110
b100 !
b100 4
b11 *
b11 3
#4120
b101 !
b101 4
b100 *
b100 3
#4130
b110 !
b110 4
b101 *
b101 3
#4140
b111 !
b111 4
b110 *
b110 3
#4150
b1000 !
b1000 4
b111 *
b111 3
#4160
b1 !
b1 4
b0 *
b0 3
#4170
b10 !
b10 4
b1 *
b1 3
#4180
b11 !
b11 4
b10 *
b10 3
#4190
b100 !
b100 4
b11 *
b11 3
#4200
b101 !
b101 4
b100 *
b100 3
#4210
b110 !
b110 4
b101 *
b101 3
#4220
b111 !
b111 4
b110 *
b110 3
#4230
b1000 !
b1000 4
b111 *
b111 3
#4240
b1 !
b1 4
b0 *
b0 3
#4250
b10 !
b10 4
b1 *
b1 3
#4260
b11 !
b11 4
b10 *
b10 3
#4270
b100 !
b100 4
b11 *
b11 3
#4280
b101 !
b101 4
b100 *
b100 3
#4290
b110 !
b110 4
b101 *
b101 3
#4300
b111 !
b111 4
b110 *
b110 3
#4310
b1000 !
b1000 4
b111 *
b111 3
#4320
b1 !
b1 4
b0 *
b0 3
#4330
b10 !
b10 4
b1 *
b1 3
#4340
b11 !
b11 4
b10 *
b10 3
#4350
b100 !
b100 4
b11 *
b11 3
#4360
b101 !
b101 4
b100 *
b100 3
#4370
b110 !
b110 4
b101 *
b101 3
#4380
b111 !
b111 4
b110 *
b110 3
#4390
b1000 !
b1000 4
b111 *
b111 3
#4400
b1 !
b1 4
b0 *
b0 3
#4410
b10 !
b10 4
b1 *
b1 3
#4420
b11 !
b11 4
b10 *
b10 3
#4430
b100 !
b100 4
b11 *
b11 3
#4440
b101 !
b101 4
b100 *
b100 3
#4450
b110 !
b110 4
b101 *
b101 3
#4460
b111 !
b111 4
b110 *
b110 3
#4470
b1000 !
b1000 4
b111 *
b111 3
#4480
b1 !
b1 4
b0 *
b0 3
#4490
b10 !
b10 4
b1 *
b1 3
#4500
b11 !
b11 4
b10 *
b10 3
#4510
b100 !
b100 4
b11 *
b11 3
#4520
b101 !
b101 4
b100 *
b100 3
#4530
b110 !
b110 4
b101 *
b101 3
#4540
b111 !
b111 4
b110 *
b110 3
#4550
b1000 !
b1000 4
b111 *
b111 3
#4560
b1 !
b1 4
b0 *
b0 3
#4570
b10 !
b10 4
b1 *
b1 3
#4580
b11 !
b11 4
b10 *
b10 3
#4590
b100 !
b100 4
b11 *
b11 3
#4600
b101 !
b101 4
b100 *
b100 3
#4610
b110 !
b110 4
b101 *
b101 3
#4620
b111 !
b111 4
b110 *
b110 3
#4630
b1000 !
b1000 4
b111 *
b111 3
#4640
b1 !
b1 4
b0 *
b0 3
#4650
b10 !
b10 4
b1 *
b1 3
#4660
b11 !
b11 4
b10 *
b10 3
#4670
b100 !
b100 4
b11 *
b11 3
#4680
b101 !
b101 4
b100 *
b100 3
#4690
b110 !
b110 4
b101 *
b101 3
#4700
b111 !
b111 4
b110 *
b110 3
#4710
b1000 !
b1000 4
b111 *
b111 3
#4720
b1 !
b1 4
b0 *
b0 3
#4730
b10 !
b10 4
b1 *
b1 3
#4740
b11 !
b11 4
b10 *
b10 3
#4750
b100 !
b100 4
b11 *
b11 3
#4760
b101 !
b101 4
b100 *
b100 3
#4770
b110 !
b110 4
b101 *
b101 3
#4780
b111 !
b111 4
b110 *
b110 3
#4790
b1000 !
b1000 4
b111 *
b111 3
#4800
b1 !
b1 4
b0 *
b0 3
#4810
b10 !
b10 4
b1 *
b1 3
#4820
b11 !
b11 4
b10 *
b10 3
#4830
b100 !
b100 4
b11 *
b11 3
#4840
b101 !
b101 4
b100 *
b100 3
#4850
b110 !
b110 4
b101 *
b101 3
#4860
b111 !
b111 4
b110 *
b110 3
#4870
b1000 !
b1000 4
b111 *
b111 3
#4880
b1 !
b1 4
b0 *
b0 3
#4890
b10 !
b10 4
b1 *
b1 3
#4900
b11 !
b11 4
b10 *
b10 3
#4910
b100 !
b100 4
b11 *
b11 3
#4920
b101 !
b101 4
b100 *
b100 3
#4930
b110 !
b110 4
b101 *
b101 3
#4940
b111 !
b111 4
b110 *
b110 3
#4950
b1000 !
b1000 4
b111 *
b111 3
#4960
b1 !
b1 4
b0 *
b0 3
#4970
b10 !
b10 4
b1 *
b1 3
#4980
b11 !
b11 4
b10 *
b10 3
#4990
b100 !
b100 4
b11 *
b11 3
#5000
b101 !
b101 4
b100 *
b100 3
#5010
b110 !
b110 4
b101 *
b101 3
#5020
b111 !
b111 4
b110 *
b110 3
#5030
b1000 !
b1000 4
b111 *
b111 3
#5040
b1 !
b1 4
b0 *
b0 3
#5050
b10 !
b10 4
b1 *
b1 3
#5060
b11 !
b11 4
b10 *
b10 3
#5070
b100 !
b100 4
b11 *
b11 3
#5080
b101 !
b101 4
b100 *
b100 3
#5090
b110 !
b110 4
b101 *
b101 3
#5100
b111 !
b111 4
b110 *
b110 3
#5110
b1000 !
b1000 4
b111 *
b111 3
#5120
b1 !
b1 4
b0 *
b0 3
#5130
b10 !
b10 4
b1 *
b1 3
#5140
b11 !
b11 4
b10 *
b10 3
#5150
b100 !
b100 4
b11 *
b11 3
#5160
b101 !
b101 4
b100 *
b100 3
#5170
b110 !
b110 4
b101 *
b101 3
#5180
b111 !
b111 4
b110 *
b110 3
#5190
b1000 !
b1000 4
b111 *
b111 3
#5200
b1 !
b1 4
b0 *
b0 3
#5210
b10 !
b10 4
b1 *
b1 3
#5220
b11 !
b11 4
b10 *
b10 3
#5230
b100 !
b100 4
b11 *
b11 3
#5240
b101 !
b101 4
b100 *
b100 3
#5250
b110 !
b110 4
b101 *
b101 3
#5260
b111 !
b111 4
b110 *
b110 3
#5270
b1000 !
b1000 4
b111 *
b111 3
#5280
b1 !
b1 4
b0 *
b0 3
#5290
b10 !
b10 4
b1 *
b1 3
#5300
b11 !
b11 4
b10 *
b10 3
#5310
b100 !
b100 4
b11 *
b11 3
#5320
b101 !
b101 4
b100 *
b100 3
#5330
b110 !
b110 4
b101 *
b101 3
#5340
b111 !
b111 4
b110 *
b110 3
#5350
b1000 !
b1000 4
b111 *
b111 3
#5360
b1 !
b1 4
b0 *
b0 3
#5370
b10 !
b10 4
b1 *
b1 3
#5380
b11 !
b11 4
b10 *
b10 3
#5390
b100 !
b100 4
b11 *
b11 3
#5400
b101 !
b101 4
b100 *
b100 3
#5410
b110 !
b110 4
b101 *
b101 3
#5420
b111 !
b111 4
b110 *
b110 3
#5430
b1000 !
b1000 4
b111 *
b111 3
#5440
b1 !
b1 4
b0 *
b0 3
#5450
b10 !
b10 4
b1 *
b1 3
#5460
b11 !
b11 4
b10 *
b10 3
#5470
b100 !
b100 4
b11 *
b11 3
#5480
b101 !
b101 4
b100 *
b100 3
#5490
b110 !
b110 4
b101 *
b101 3
#5500
b111 !
b111 4
b110 *
b110 3
#5510
b1000 !
b1000 4
b111 *
b111 3
#5520
b1 !
b1 4
b0 *
b0 3
#5530
b10 !
b10 4
b1 *
b1 3
#5540
b11 !
b11 4
b10 *
b10 3
#5550
b100 !
b100 4
b11 *
b11 3
#5560
b101 !
b101 4
b100 *
b100 3
#5570
b110 !
b110 4
b101 *
b101 3
#5580
b111 !
b111 4
b110 *
b110 3
#5590
b1000 !
b1000 4
b111 *
b111 3
#5600
b1 !
b1 4
b0 *
b0 3
#5610
b10 !
b10 4
b1 *
b1 3
#5620
b11 !
b11 4
b10 *
b10 3
#5630
b100 !
b100 4
b11 *
b11 3
#5640
b101 !
b101 4
b100 *
b100 3
#5650
b110 !
b110 4
b101 *
b101 3
#5660
b111 !
b111 4
b110 *
b110 3
#5670
b1000 !
b1000 4
b111 *
b111 3
#5680
b1 !
b1 4
b0 *
b0 3
