encoder3to8.v
module PriorityEncoder8to3 (
    input [7:0] I,  // 8 input lines
    output reg [2:0] Y,  // 3-bit output encoding the highest active input
    output reg V  // Valid output signal
);

    always @(*) begin
        case (1'b1)
            I[7]: begin Y = 3'b111; V = 1; end
            I[6]: begin Y = 3'b110; V = 1; end
            I[5]: begin Y = 3'b101; V = 1; end
            I[4]: begin Y = 3'b100; V = 1; end
            I[3]: begin Y = 3'b011; V = 1; end
            I[2]: begin Y = 3'b010; V = 1; end
            I[1]: begin Y = 3'b001; V = 1; end
            I[0]: begin Y = 3'b000; V = 1; end
            default: begin Y = 3'b000; V = 0; end
        endcase
    end

endmodule

encoder3to8_tb.v
module tb_PriorityEncoder8to3;
    reg [7:0] I;  // 8-bit input
    wire [2:0] Y;  // 3-bit output
    wire V;  // Valid output

    // Instantiate the Priority Encoder
    PriorityEncoder8to3 uut (
        .I(I),
        .Y(Y),
        .V(V)
    );

    initial begin
        // Dump waveforms for GTKWave
        $dumpfile("priority_encoder.vcd");
        $dumpvars(0, tb_PriorityEncoder8to3);
        
        // Test all combinations of inputs
        I = 8'b00000000; #10;
        I = 8'b00000001; #10;
        I = 8'b00000010; #10;
        I = 8'b00000100; #10;
        I = 8'b00001000; #10;
        I = 8'b00010000; #10;
        I = 8'b00100000; #10;
        I = 8'b01000000; #10;
        I = 8'b10000000; #10;
        I = 8'b11111111; #10;
        
        // End simulation
        $finish;
    end
endmodule

priority_encoder.vcd
$date
	Wed Dec 11 17:32:49 2024
$end
$version
	Icarus Verilog
$end
$timescale
	1s
$end
$scope module tb_PriorityEncoder8to3 $end
$var wire 3 ! Y [2:0] $end
$var wire 1 " V $end
$var reg 8 # I [7:0] $end
$scope module uut $end
$var wire 8 $ I [7:0] $end
$var reg 1 " V $end
$var reg 3 % Y [2:0] $end
$upscope $end
$upscope $end
$enddefinitions $end
#0
$dumpvars
b0 %
b0 $
b0 #
0"
b0 !
$end
#10
1"
b1 #
b1 $
#20
b1 !
b1 %
b10 #
b10 $
#30
b10 !
b10 %
b100 #
b100 $
#40
b11 !
b11 %
b1000 #
b1000 $
#50
b100 !
b100 %
b10000 #
b10000 $
#60
b101 !
b101 %
b100000 #
b100000 $
#70
b110 !
b110 %
b1000000 #
b1000000 $
#80
b111 !
b111 %
b10000000 #
b10000000 $
#90
b11111111 #
b11111111 $
