state.v
module sequence_detector (
    input clk,          // Clock signal
    input reset,        // Asynchronous reset signal
    input in,           // Serial input bit stream
    output reg detected // Output signal, high when "101101" is detected
);

    // Define states using parameters
    parameter S0 = 3'b000, // Initial state
              S1 = 3'b001,
              S2 = 3'b010,
              S3 = 3'b011,
              S4 = 3'b100,
              S5 = 3'b101,
              S6 = 3'b110; // Sequence detected state

    reg [2:0] state, next_state; // State registers

    // State transition logic
    always @ (posedge clk or posedge reset) begin
        if (reset)
            state <= S0; // Reset to initial state
        else
            state <= next_state; // Transition to next state
    end

    // Next state logic
    always @ (state or in) begin
        case (state)
            S0: next_state = (in) ? S1 : S0; // If in = 1, move to S1, else stay in S0
            S1: next_state = (in) ? S1 : S2; // If in = 0, move to S2
            S2: next_state = (in) ? S3 : S0; // If in = 1, move to S3, else reset to S0
            S3: next_state = (in) ? S3 : S4; // If in = 0, move to S4
            S4: next_state = (in) ? S5 : S0; // If in = 1, move to S5, else reset to S0
            S5: next_state = (in) ? S1 : S6; // If in = 0, move to S6 (sequence complete)
            S6: next_state = S6; // Once in S6, stay in S6 (sequence detected)
            default: next_state = S0; // Default to S0 on invalid state
        endcase
    end

    // Output logic
    always @ (state) begin
        if (state == S6)
            detected = 1; // Set detected signal high when the sequence is detected
        else
            detected = 0;
    end

endmodule

state_tb.v
module tb_sequence_detector;

    reg clk;
    reg reset;
    reg in;
    wire detected;

    // Instantiate the sequence detector module
    sequence_detector uut (
        .clk(clk),
        .reset(reset),
        .in(in),
        .detected(detected)
    );

    // Generate clock signal
    always #5 clk = ~clk;

    // Test sequence
    initial begin
        // Initialize signals
        clk = 0;
        reset = 1;
        in = 0;

        // Apply reset
        #10 reset = 0;

        // Apply the sequence "101101"
        #10 in = 1; // S0 -> S1
        #10 in = 0; // S1 -> S2
        #10 in = 1; // S2 -> S3
        #10 in = 1; // S3 -> S4
        #10 in = 0; // S4 -> S5
        #10 in = 1; // S5 -> S6 (detected = 1)

        // Test with other sequences
        #10 in = 0;
        #10 in = 1;
        #10 in = 0;
        #10 in = 1; // Should not detect

        // Finish the simulation
        #100 $finish;
    end

    // Dump the waveform for GTKWave
    initial begin
        $dumpfile("sequence_detector.vcd");
        $dumpvars(0, tb_sequence_detector);
    end

endmodule

sequence_detector.vcd
$date
	Wed Dec 11 20:39:10 2024
$end
$version
	Icarus Verilog
$end
$timescale
	1s
$end
$scope module tb_sequence_detector $end
$var wire 1 ! detected $end
$var reg 1 " clk $end
$var reg 1 # in $end
$var reg 1 $ reset $end
$scope module uut $end
$var wire 1 " clk $end
$var wire 1 # in $end
$var wire 1 $ reset $end
$var reg 1 ! detected $end
$var reg 3 % next_state [2:0] $end
$var reg 3 & state [2:0] $end
$upscope $end
$upscope $end
$enddefinitions $end
#0
$dumpvars
b0 &
b0 %
1$
0#
0"
0!
$end
#5
1"
#10
0"
0$
#15
1"
#20
b1 %
0"
1#
#25
b1 &
1"
#30
b10 %
0"
0#
#35
b0 %
b10 &
1"
#40
b11 %
0"
1#
#45
b11 &
1"
#50
0"
#55
1"
#60
b100 %
0"
0#
#65
b0 %
b100 &
1"
#70
b101 %
0"
1#
#75
b1 %
b101 &
1"
#80
b110 %
0"
0#
#85
1!
b110 &
1"
#90
0"
1#
#95
1"
#100
0"
0#
#105
1"
#110
0"
1#
