register2.v
module shift_register (
    input [7:0] D,        // 8-bit data input
    input reset,          // Asynchronous reset
    input enable,         // Enable signal
    input clk,            // Clock signal
    output reg [7:0] Q    // 8-bit output (final stage)
);

    // Create a 5-stage shift register
    reg [7:0] stage_1, stage_2, stage_3, stage_4, stage_5;

    always @(posedge clk or posedge reset) begin
        if (reset) begin
            // Reset all stages when reset is high
            stage_1 <= 8'b00000000;
            stage_2 <= 8'b00000000;
            stage_3 <= 8'b00000000;
            stage_4 <= 8'b00000000;
            stage_5 <= 8'b00000000;
        end else if (enable) begin
            // Shift data through the stages when enable is high
            stage_1 <= D;
            stage_2 <= stage_1;
            stage_3 <= stage_2;
            stage_4 <= stage_3;
            stage_5 <= stage_4;
        end
    end

    // Output the value of the last stage
    always @(stage_5) begin
        Q <= stage_5;
    end
    
endmodule

register2_tb.v
module tb_shift_register;
    reg [7:0] D;          // 8-bit data input
    reg reset;            // Asynchronous reset
    reg enable;           // Enable signal
    reg clk;              // Clock signal
    wire [7:0] Q;         // 8-bit output

    // Instantiate the shift register
    shift_register uut (
        .D(D),
        .reset(reset),
        .enable(enable),
        .clk(clk),
        .Q(Q)
    );

    // Clock generation
    always begin
        #5 clk = ~clk;  // Clock toggles every 5 time units
    end

    initial begin
        // Initialize signals
        clk = 0;
        reset = 0;
        enable = 0;
        D = 8'b00000000;

        // Dump waveform for GTKWave
        $dumpfile("shift_register_wave.vcd");
        $dumpvars(0, tb_shift_register);

        // Test case 1: Assert reset
        reset = 1;   // Assert reset
        #10;          // Wait for 10 time units
        reset = 0;    // Deassert reset
        #10;

        // Test case 2: Enable and shift data (0xAA)
        enable = 1;
        D = 8'b10101010;  // Load 0xAA
        #10;              // Wait for a clock edge

        // Test case 3: Disable enable (no shifting)
        enable = 0;
        D = 8'b11001100;  // Attempt to load 0xCC, but enable is off
        #10;

        // Test case 4: Shift data again (0xFF)
        enable = 1;
        D = 8'b11111111;  // Load 0xFF
        #50;

        $finish;
    end
endmodule

shift_register_wave.vcd
$date
	Wed Dec 11 19:10:04 2024
$end
$version
	Icarus Verilog
$end
$timescale
	1s
$end
$scope module tb_shift_register $end
$var wire 8 ! Q [7:0] $end
$var reg 8 " D [7:0] $end
$var reg 1 # clk $end
$var reg 1 $ enable $end
$var reg 1 % reset $end
$scope module uut $end
$var wire 8 & D [7:0] $end
$var wire 1 # clk $end
$var wire 1 $ enable $end
$var wire 1 % reset $end
$var reg 8 ' Q [7:0] $end
$var reg 8 ( stage_1 [7:0] $end
$var reg 8 ) stage_2 [7:0] $end
$var reg 8 * stage_3 [7:0] $end
$var reg 8 + stage_4 [7:0] $end
$var reg 8 , stage_5 [7:0] $end
$upscope $end
$upscope $end
$enddefinitions $end
#0
$dumpvars
b0 ,
b0 +
b0 *
b0 )
b0 (
b0 '
b0 &
1%
0$
0#
b0 "
b0 !
$end
#5
1#
#10
0#
0%
#15
1#
#20
0#
b10101010 "
b10101010 &
1$
#25
b10101010 (
1#
#30
0#
b11001100 "
b11001100 &
0$
#35
1#
#40
0#
b11111111 "
b11111111 &
1$
#45
b10101010 )
b11111111 (
1#
#50
0#
#55
b10101010 *
b11111111 )
1#
#60
0#
#65
b10101010 +
b11111111 *
1#
#70
0#
#75
b10101010 !
b10101010 '
b10101010 ,
b11111111 +
1#
#80
0#
#85
b11111111 !
b11111111 '
b11111111 ,
1#
