random/test2.v
module mux_8_1(o, i, s);
    output o;             // Output of the 8-to-1 multiplexer
    input [7:0] i;        // 8 input lines
    input [2:0] s;        // 3 select lines

    wire [3:0] k1;        // Intermediate wires for level 1
    wire [1:0] k2;        // Intermediate wires for level 2

    // first level
    mux_case mux1(k1[0], i[1:0], s[0]);
    mux_case mux2(k1[1], i[3:2], s[0]);
    mux_case mux3(k1[2], i[5:4], s[0]);
    mux_case mux4(k1[3], i[7:6], s[0]);

    // second level
    mux_case mux5(k2[0], k1[1:0], s[1]);
    mux_case mux6(k2[1], k1[3:2], s[1]);

    // third level
    mux_case mux7(o, k2[1:0], s[2]);
endmodule

// Definition of 2-to-1 multiplexer module
module mux_case(out, in, s);
    output reg out;       // Single output
    input [1:0] in;      // 2 inputs
    input s;             // Select line

    always @(*) begin
        case (s)
            1'b0: out = in[0];
            1'b1: out = in[1];
            default: out = 1'bx; // Safety fallback
        endcase
    end
endmodule

random/test2_tb.v
module tb_mux_8_1();
    reg [7:0] i;       // 8 inputs
    reg [2:0] s;       // 3 select lines
    wire o;            // Output

    mux_8_1 uut(o, i, s); // Instantiate the 8-to-1 multiplexer

    initial begin
        $dumpfile("dump.vcd");   // Specify the VCD output file name
        $dumpvars(0, tb_mux_8_1); // Dump all variables in the testbench
        
        i = 8'b10101010;         // Example input vector
        for (s = 0; s < 8; s = s + 1) begin
            #10;               
            $display("s = %b, o = %b", s, o); // Display the selected output
        end
        $finish;                 // End the simulation
    end
endmodule

random/dump.vcd
$date
	Wed Dec 11 13:03:39 2024
$end
$version
	Icarus Verilog
$end
$timescale
	1s
$end
$scope module tb_mux_8_1 $end
$var wire 1 ! o $end
$var reg 8 " i [7:0] $end
$var reg 3 # s [2:0] $end
$scope module uut $end
$var wire 8 $ i [7:0] $end
$var wire 3 % s [2:0] $end
$var wire 1 ! o $end
$var wire 2 & k2 [1:0] $end
$var wire 4 ' k1 [3:0] $end
$scope module mux1 $end
$var wire 2 ( in [1:0] $end
$var wire 1 ) s $end
$var reg 1 * out $end
$upscope $end
$scope module mux2 $end
$var wire 2 + in [1:0] $end
$var wire 1 , s $end
$var reg 1 - out $end
$upscope $end
$scope module mux3 $end
$var wire 2 . in [1:0] $end
$var wire 1 / s $end
$var reg 1 0 out $end
$upscope $end
$scope module mux4 $end
$var wire 2 1 in [1:0] $end
$var wire 1 2 s $end
$var reg 1 3 out $end
$upscope $end
$scope module mux5 $end
$var wire 2 4 in [1:0] $end
$var wire 1 5 s $end
$var reg 1 6 out $end
$upscope $end
$scope module mux6 $end
$var wire 2 7 in [1:0] $end
$var wire 1 8 s $end
$var reg 1 9 out $end
$upscope $end
$scope module mux7 $end
$var wire 2 : in [1:0] $end
$var wire 1 ; s $end
$var reg 1 ! out $end
$upscope $end
$upscope $end
$upscope $end
$enddefinitions $end
#0
$dumpvars
0;
b0 :
09
08
b0 7
06
05
b0 4
03
02
b10 1
00
0/
b10 .
0-
0,
b10 +
0*
0)
b10 (
b0 '
b0 &
b0 %
b10101010 $
b0 #
b10101010 "
0!
$end
#10
1!
16
b11 &
b11 :
19
b11 4
b11 7
1*
1-
10
b1111 '
13
1)
1,
1/
12
b1 #
b1 %
#20
0!
06
b0 &
b0 :
09
b0 4
b0 7
0*
0-
00
b0 '
03
0)
0,
0/
02
15
18
b10 #
b10 %
#30
1!
16
b11 &
b11 :
19
b11 4
b11 7
1*
1-
10
b1111 '
13
1)
1,
1/
12
b11 #
b11 %
#40
0!
06
b0 &
b0 :
09
b0 4
b0 7
0*
0-
00
b0 '
03
0)
0,
0/
02
05
08
1;
b100 #
b100 %
#50
1!
16
b11 &
b11 :
19
b11 4
b11 7
1*
1-
10
b1111 '
13
1)
1,
1/
12
b101 #
b101 %
#60
0!
06
b0 &
b0 :
09
b0 4
b0 7
0*
0-
00
b0 '
03
0)
0,
0/
02
15
18
b110 #
b110 %
#70
1!
16
b11 &
b11 :
19
b11 4
b11 7
1*
1-
10
b1111 '
13
1)
1,
1/
12
b111 #
b111 %
#80
0!
06
b0 &
b0 :
09
b0 4
b0 7
0*
0-
00
b0 '
03
0)
0,
0/
02
05
08
0;
b0 #
b0 %
#90
1!
16
b11 &
b11 :
19
b11 4
b11 7
1*
1-
10
b1111 '
13
1)
1,
1/
12
b1 #
b1 %
#100
0!
06
b0 &
b0 :
09
b0 4
b0 7
0*
0-
00
b0 '
03
0)
0,
0/
02
15
18
b10 #
b10 %
#110
1!
16
b11 &
b11 :
19
b11 4
b11 7
1*
1-
10
b1111 '
13
1)
1,
1/
12
b11 #
b11 %
#120
0!
06
b0 &
b0 :
09
b0 4
b0 7
0*
0-
00
b0 '
03
0)
0,
0/
02
05
08
1;
b100 #
b100 %
#130
1!
16
b11 &
b11 :
19
b11 4
b11 7
1*
1-
10
b1111 '
13
1)
1,
1/
12
b101 #
b101 %
#140
0!
06
b0 &
b0 :
09
b0 4
b0 7
0*
0-
00
b0 '
03
0)
0,
0/
02
15
18
b110 #
b110 %
#150
1!
16
b11 &
b11 :
19
b11 4
b11 7
1*
1-
10
b1111 '
13
1)
1,
1/
12
b111 #
b111 %
#160
0!
06
b0 &
b0 :
09
b0 4
b0 7
0*
0-
00
b0 '
03
0)
0,
0/
02
05
08
0;
b0 #
b0 %
#170
1!
16
b11 &
b11 :
19
b11 4
b11 7
1*
1-
10
b1111 '
13
1)
1,
1/
12
b1 #
b1 %
#180
0!
06
b0 &
b0 :
09
b0 4
b0 7
0*
0-
00
b0 '
03
0)
0,
0/
02
15
18
b10 #
b10 %
#190
1!
16
b11 &
b11 :
19
b11 4
b11 7
1*
1-
10
b1111 '
13
1)
1,
1/
12
b11 #
b11 %
#200
0!
06
b0 &
b0 :
09
b0 4
b0 7
0*
0-
00
b0 '
03
0)
0,
0/
02
05
08
1;
b100 #
b100 %
#210
1!
16
b11 &
b11 :
19
b11 4
b11 7
1*
1-
10
b1111 '
13
1)
1,
1/
12
b101 #
b101 %
#220
0!
06
b0 &
b0 :
09
b0 4
b0 7
0*
0-
00
b0 '
03
0)
0,
0/
02
15
18
b110 #
b110 %
#230
1!
16
b11 &
b11 :
19
b11 4
b11 7
1*
1-
10
b1111 '
13
1)
1,
1/
12
b111 #
b111 %
#240
0!
06
b0 &
b0 :
09
b0 4
b0 7
0*
0-
00
b0 '
03
0)
0,
0/
02
05
08
0;
b0 #
b0 %
#250
1!
16
b11 &
b11 :
19
b11 4
b11 7
1*
1-
10
b1111 '
13
1)
1,
1/
12
b1 #
b1 %
#260
0!
06
b0 &
b0 :
09
b0 4
b0 7
0*
0-
00
b0 '
03
0)
0,
0/
02
15
18
b10 #
b10 %
#270
1!
16
b11 &
b11 :
19
b11 4
b11 7
1*
1-
10
b1111 '
13
1)
1,
1/
12
b11 #
b11 %
#280
0!
06
b0 &
b0 :
09
b0 4
b0 7
0*
0-
00
b0 '
03
0)
0,
0/
02
05
08
1;
b100 #
b100 %
#290
1!
16
b11 &
b11 :
19
b11 4
b11 7
1*
1-
10
b1111 '
13
1)
1,
1/
12
b101 #
b101 %
#300
0!
06
b0 &
b0 :
09
b0 4
b0 7
0*
0-
00
b0 '
03
0)
0,
0/
02
15
18
b110 #
b110 %
#310
1!
16
b11 &
b11 :
19
b11 4
b11 7
1*
1-
10
b1111 '
13
1)
1,
1/
12
b111 #
b111 %
#320
0!
06
b0 &
b0 :
09
b0 4
b0 7
0*
0-
00
b0 '
03
0)
0,
0/
02
05
08
0;
b0 #
b0 %
#330
1!
16
b11 &
b11 :
19
b11 4
b11 7
1*
1-
10
b1111 '
13
1)
1,
1/
12
b1 #
b1 %
#340
0!
06
b0 &
b0 :
09
b0 4
b0 7
0*
0-
00
b0 '
03
0)
0,
0/
02
15
18
b10 #
b10 %
#350
1!
16
b11 &
b11 :
19
b11 4
b11 7
1*
1-
10
b1111 '
13
1)
1,
1/
12
b11 #
b11 %
#360
0!
06
b0 &
b0 :
09
b0 4
b0 7
0*
0-
00
b0 '
03
0)
0,
0/
02
05
08
1;
b100 #
b100 %
#370
1!
16
b11 &
b11 :
19
b11 4
b11 7
1*
1-
10
b1111 '
13
1)
1,
1/
12
b101 #
b101 %
#380
0!
06
b0 &
b0 :
09
b0 4
b0 7
0*
0-
00
b0 '
03
0)
0,
0/
02
15
18
b110 #
b110 %
#390
1!
16
b11 &
b11 :
19
b11 4
b11 7
1*
1-
10
b1111 '
13
1)
1,
1/
12
b111 #
b111 %
#400
0!
06
b0 &
b0 :
09
b0 4
b0 7
0*
0-
00
b0 '
03
0)
0,
0/
02
05
08
0;
b0 #
b0 %
#410
1!
16
b11 &
b11 :
19
b11 4
b11 7
1*
1-
10
b1111 '
13
1)
1,
1/
12
b1 #
b1 %
#420
0!
06
b0 &
b0 :
09
b0 4
b0 7
0*
0-
00
b0 '
03
0)
0,
0/
02
15
18
b10 #
b10 %
#430
1!
16
b11 &
b11 :
19
b11 4
b11 7
1*
1-
10
b1111 '
13
1)
1,
1/
12
b11 #
b11 %
#440
0!
06
b0 &
b0 :
09
b0 4
b0 7
0*
0-
00
b0 '
03
0)
0,
0/
02
05
08
1;
b100 #
b100 %
#450
1!
16
b11 &
b11 :
19
b11 4
b11 7
1*
1-
10
b1111 '
13
1)
1,
1/
12
b101 #
b101 %
#460
0!
06
b0 &
b0 :
09
b0 4
b0 7
0*
0-
00
b0 '
03
0)
0,
0/
02
15
18
b110 #
b110 %
#470
1!
16
b11 &
b11 :
19
b11 4
b11 7
1*
1-
10
b1111 '
13
1)
1,
1/
12
b111 #
b111 %
#480
0!
06
b0 &
b0 :
09
b0 4
b0 7
0*
0-
00
b0 '
03
0)
0,
0/
02
05
08
0;
b0 #
b0 %
#490
1!
16
b11 &
b11 :
19
b11 4
b11 7
1*
1-
10
b1111 '
13
1)
1,
1/
12
b1 #
b1 %
#500
0!
06
b0 &
b0 :
09
b0 4
b0 7
0*
0-
00
b0 '
03
0)
0,
0/
02
15
18
b10 #
b10 %
#510
1!
16
b11 &
b11 :
19
b11 4
b11 7
1*
1-
10
b1111 '
13
1)
1,
1/
12
b11 #
b11 %
#520
0!
06
b0 &
b0 :
09
b0 4
b0 7
0*
0-
00
b0 '
03
0)
0,
0/
02
05
08
1;
b100 #
b100 %
#530
1!
16
b11 &
b11 :
19
b11 4
b11 7
1*
1-
10
b1111 '
13
1)
1,
1/
12
b101 #
b101 %
#540
0!
06
b0 &
b0 :
09
b0 4
b0 7
0*
0-
00
b0 '
03
0)
0,
0/
02
15
18
b110 #
b110 %
#550
1!
16
b11 &
b11 :
19
b11 4
b11 7
1*
1-
10
b1111 '
13
1)
1,
1/
12
b111 #
b111 %
#560
0!
06
b0 &
b0 :
09
b0 4
b0 7
0*
0-
00
b0 '
03
0)
0,
0/
02
05
08
0;
b0 #
b0 %
#570
1!
16
b11 &
b11 :
19
b11 4
b11 7
1*
1-
10
b1111 '
13
1)
1,
1/
12
b1 #
b1 %
#580
0!
06
b0 &
b0 :
09
b0 4
b0 7
0*
0-
00
b0 '
03
0)
0,
0/
02
15
18
b10 #
b10 %
#590
1!
16
b11 &
b11 :
19
b11 4
b11 7
1*
1-
10
b1111 '
13
1)
1,
1/
12
b11 #
b11 %
#600
0!
06
b0 &
b0 :
09
b0 4
b0 7
0*
0-
00
b0 '
03
0)
0,
0/
02
05
08
1;
b100 #
b100 %
#610
1!
16
b11 &
b11 :
19
b11 4
b11 7
1*
1-
10
b1111 '
13
1)
1,
1/
12
b101 #
b101 %
#620
0!
06
b0 &
b0 :
09
b0 4
b0 7
0*
0-
00
b0 '
03
0)
0,
0/
02
15
18
b110 #
b110 %
#630
1!
16
b11 &
b11 :
19
b11 4
b11 7
1*
1-
10
b1111 '
13
1)
1,
1/
12
b111 #
b111 %
#640
0!
06
b0 &
b0 :
09
b0 4
b0 7
0*
0-
00
b0 '
03
0)
0,
0/
02
05
08
0;
b0 #
b0 %
#650
1!
16
b11 &
b11 :
19
b11 4
b11 7
1*
1-
10
b1111 '
13
1)
1,
1/
12
b1 #
b1 %
#660
0!
06
b0 &
b0 :
09
b0 4
b0 7
0*
0-
00
b0 '
03
0)
0,
0/
02
15
18
b10 #
b10 %
#670
1!
16
b11 &
b11 :
19
b11 4
b11 7
1*
1-
10
b1111 '
13
1)
1,
1/
12
b11 #
b11 %
#680
0!
06
b0 &
b0 :
09
b0 4
b0 7
0*
0-
00
b0 '
03
0)
0,
0/
02
05
08
1;
b100 #
b100 %
#690
1!
16
b11 &
b11 :
19
b11 4
b11 7
1*
1-
10
b1111 '
13
1)
1,
1/
12
b101 #
b101 %
#700
0!
06
b0 &
b0 :
09
b0 4
b0 7
0*
0-
00
b0 '
03
0)
0,
0/
02
15
18
b110 #
b110 %
#710
1!
16
b11 &
b11 :
19
b11 4
b11 7
1*
1-
10
b1111 '
13
1)
1,
1/
12
b111 #
b111 %
#720
0!
06
b0 &
b0 :
09
b0 4
b0 7
0*
0-
00
b0 '
03
0)
0,
0/
02
05
08
0;
b0 #
b0 %
#730
1!
16
b11 &
b11 :
19
b11 4
b11 7
1*
1-
10
b1111 '
13
1)
1,
1/
12
b1 #
b1 %
#740
0!
06
b0 &
b0 :
09
b0 4
b0 7
0*
0-
00
b0 '
03
0)
0,
0/
02
15
18
b10 #
b10 %
#750
1!
16
b11 &
b11 :
19
b11 4
b11 7
1*
1-
10
b1111 '
13
1)
1,
1/
12
b11 #
b11 %
#760
0!
06
b0 &
b0 :
09
b0 4
b0 7
0*
0-
00
b0 '
03
0)
0,
0/
02
05
08
1;
b100 #
b100 %
#770
1!
16
b11 &
b11 :
19
b11 4
b11 7
1*
1-
10
b1111 '
13
1)
1,
1/
12
b101 #
b101 %
#780
0!
06
b0 &
b0 :
09
b0 4
b0 7
0*
0-
00
b0 '
03
0)
0,
0/
02
15
18
b110 #
b110 %
#790
1!
16
b11 &
b11 :
19
b11 4
b11 7
1*
1-
10
b1111 '
13
1)
1,
1/
12
b111 #
b111 %
#800
0!
06
b0 &
b0 :
09
b0 4
b0 7
0*
0-
00
b0 '
03
0)
0,
0/
02
05
08
0;
b0 #
b0 %
#810
1!
16
b11 &
b11 :
19
b11 4
b11 7
1*
1-
10
b1111 '
13
1)
1,
1/
12
b1 #
b1 %
#820
0!
06
b0 &
b0 :
09
b0 4
b0 7
0*
0-
00
b0 '
03
0)
0,
0/
02
15
18
b10 #
b10 %
#830
1!
16
b11 &
b11 :
19
b11 4
b11 7
1*
1-
10
b1111 '
13
1)
1,
1/
12
b11 #
b11 %
#840
0!
06
b0 &
b0 :
09
b0 4
b0 7
0*
0-
00
b0 '
03
0)
0,
0/
02
05
08
1;
b100 #
b100 %
#850
1!
16
b11 &
b11 :
19
b11 4
b11 7
1*
1-
10
b1111 '
13
1)
1,
1/
12
b101 #
b101 %
#860
0!
06
b0 &
b0 :
09
b0 4
b0 7
0*
0-
00
b0 '
03
0)
0,
0/
02
15
18
b110 #
b110 %
#870
1!
16
b11 &
b11 :
19
b11 4
b11 7
1*
1-
10
b1111 '
13
1)
1,
1/
12
b111 #
b111 %
#880
0!
06
b0 &
b0 :
09
b0 4
b0 7
0*
0-
00
b0 '
03
0)
0,
0/
02
05
08
0;
b0 #
b0 %
#890
1!
16
b11 &
b11 :
19
b11 4
b11 7
1*
1-
10
b1111 '
13
1)
1,
1/
12
b1 #
b1 %
#900
0!
06
b0 &
b0 :
09
b0 4
b0 7
0*
0-
00
b0 '
03
0)
0,
0/
02
15
18
b10 #
b10 %
#910
1!
16
b11 &
b11 :
19
b11 4
b11 7
1*
1-
10
b1111 '
13
1)
1,
1/
12
b11 #
b11 %
#920
0!
06
b0 &
b0 :
09
b0 4
b0 7
0*
0-
00
b0 '
03
0)
0,
0/
02
05
08
1;
b100 #
b100 %
#930
1!
16
b11 &
b11 :
19
b11 4
b11 7
1*
1-
10
b1111 '
13
1)
1,
1/
12
b101 #
b101 %
#940
0!
06
b0 &
b0 :
09
b0 4
b0 7
0*
0-
00
b0 '
03
0)
0,
0/
02
15
18
b110 #
b110 %
#950
1!
16
b11 &
b11 :
19
b11 4
b11 7
1*
1-
10
b1111 '
13
1)
1,
1/
12
b111 #
b111 %
#960
0!
06
b0 &
b0 :
09
b0 4
b0 7
0*
0-
00
b0 '
03
0)
0,
0/
02
05
08
0;
b0 #
b0 %
#970
1!
16
b11 &
b11 :
19
b11 4
b11 7
1*
1-
10
b1111 '
13
1)
1,
1/
12
b1 #
b1 %
#980
0!
06
b0 &
b0 :
09
b0 4
b0 7
0*
0-
00
b0 '
03
0)
0,
0/
02
15
18
b10 #
b10 %
#990
1!
16
b11 &
b11 :
19
b11 4
b11 7
1*
1-
10
b1111 '
13
1)
1,
1/
12
b11 #
b11 %
#1000
0!
06
b0 &
b0 :
09
b0 4
b0 7
0*
0-
00
b0 '
03
0)
0,
0/
02
05
08
1;
b100 #
b100 %
#1010
1!
16
b11 &
b11 :
19
b11 4
b11 7
1*
1-
10
b1111 '
13
1)
1,
1/
12
b101 #
b101 %
#1020
0!
06
b0 &
b0 :
09
b0 4
b0 7
0*
0-
00
b0 '
03
0)
0,
0/
02
15
18
b110 #
b110 %
#1030
1!
16
b11 &
b11 :
19
b11 4
b11 7
1*
1-
10
b1111 '
13
1)
1,
1/
12
b111 #
b111 %
#1040
0!
06
b0 &
b0 :
09
b0 4
b0 7
0*
0-
00
b0 '
03
0)
0,
0/
02
05
08
0;
b0 #
b0 %
#1050
1!
16
b11 &
b11 :
19
b11 4
b11 7
1*
1-
10
b1111 '
13
1)
1,
1/
12
b1 #
b1 %
#1060
0!
06
b0 &
b0 :
09
b0 4
b0 7
0*
0-
00
b0 '
03
0)
0,
0/
02
15
18
b10 #
b10 %
#1070
1!
16
b11 &
b11 :
19
b11 4
b11 7
1*
1-
10
b1111 '
13
1)
1,
1/
12
b11 #
b11 %
#1080
0!
06
b0 &
b0 :
09
b0 4
b0 7
0*
0-
00
b0 '
03
0)
0,
0/
02
05
08
1;
b100 #
b100 %
#1090
1!
16
b11 &
b11 :
19
b11 4
b11 7
1*
1-
10
b1111 '
13
1)
1,
1/
12
b101 #
b101 %
#1100
0!
06
b0 &
b0 :
09
b0 4
b0 7
0*
0-
00
b0 '
03
0)
0,
0/
02
15
18
b110 #
b110 %
#1110
1!
16
b11 &
b11 :
19
b11 4
b11 7
1*
1-
10
b1111 '
13
1)
1,
1/
12
b111 #
b111 %
#1120
0!
06
b0 &
b0 :
09
b0 4
b0 7
0*
0-
00
b0 '
03
0)
0,
0/
02
05
08
0;
b0 #
b0 %
#1130
1!
16
b11 &
b11 :
19
b11 4
b11 7
1*
1-
10
b1111 '
13
1)
1,
1/
12
b1 #
b1 %
#1140
0!
06
b0 &
b0 :
09
b0 4
b0 7
0*
0-
00
b0 '
03
0)
0,
0/
02
15
18
b10 #
b10 %
#1150
1!
16
b11 &
b11 :
19
b11 4
b11 7
1*
1-
10
b1111 '
13
1)
1,
1/
12
b11 #
b11 %
#1160
0!
06
b0 &
b0 :
09
b0 4
b0 7
0*
0-
00
b0 '
03
0)
0,
0/
02
05
08
1;
b100 #
b100 %
#1170
1!
16
b11 &
b11 :
19
b11 4
b11 7
1*
1-
10
b1111 '
13
1)
1,
1/
12
b101 #
b101 %
#1180
0!
06
b0 &
b0 :
09
b0 4
b0 7
0*
0-
00
b0 '
03
0)
0,
0/
02
15
18
b110 #
b110 %
#1190
1!
16
b11 &
b11 :
19
b11 4
b11 7
1*
1-
10
b1111 '
13
1)
1,
1/
12
b111 #
b111 %
#1200
0!
06
b0 &
b0 :
09
b0 4
b0 7
0*
0-
00
b0 '
03
0)
0,
0/
02
05
08
0;
b0 #
b0 %
#1210
1!
16
b11 &
b11 :
19
b11 4
b11 7
1*
1-
10
b1111 '
13
1)
1,
1/
12
b1 #
b1 %
#1220
0!
06
b0 &
b0 :
09
b0 4
b0 7
0*
0-
00
b0 '
03
0)
0,
0/
02
15
18
b10 #
b10 %
#1230
1!
16
b11 &
b11 :
19
b11 4
b11 7
1*
1-
10
b1111 '
13
1)
1,
1/
12
b11 #
b11 %
#1240
0!
06
b0 &
b0 :
09
b0 4
b0 7
0*
0-
00
b0 '
03
0)
0,
0/
02
05
08
1;
b100 #
b100 %
#1250
1!
16
b11 &
b11 :
19
b11 4
b11 7
1*
1-
10
b1111 '
13
1)
1,
1/
12
b101 #
b101 %
#1260
0!
06
b0 &
b0 :
09
b0 4
b0 7
0*
0-
00
b0 '
03
0)
0,
0/
02
15
18
b110 #
b110 %
#1270
1!
16
b11 &
b11 :
19
b11 4
b11 7
1*
1-
10
b1111 '
13
1)
1,
1/
12
b111 #
b111 %
#1280
0!
06
b0 &
b0 :
09
b0 4
b0 7
0*
0-
00
b0 '
03
0)
0,
0/
02
05
08
0;
b0 #
b0 %
#1290
1!
16
b11 &
b11 :
19
b11 4
b11 7
1*
1-
10
b1111 '
13
1)
1,
1/
12
b1 #
b1 %
#1300
0!
06
b0 &
b0 :
09
b0 4
b0 7
0*
0-
00
b0 '
03
0)
0,
0/
02
15
18
b10 #
b10 %
#1310
1!
16
b11 &
b11 :
19
b11 4
b11 7
1*
1-
10
b1111 '
13
1)
1,
1/
12
b11 #
b11 %
#1320
0!
06
b0 &
b0 :
09
b0 4
b0 7
0*
0-
00
b0 '
03
0)
0,
0/
02
05
08
1;
b100 #
b100 %
#1330
1!
16
b11 &
b11 :
19
b11 4
b11 7
1*
1-
10
b1111 '
13
1)
1,
1/
12
b101 #
b101 %
#1340
0!
06
b0 &
b0 :
09
b0 4
b0 7
0*
0-
00
b0 '
03
0)
0,
0/
02
15
18
b110 #
b110 %
#1350
1!
16
b11 &
b11 :
19
b11 4
b11 7
1*
1-
10
b1111 '
13
1)
1,
1/
12
b111 #
b111 %
#1360
0!
06
b0 &
b0 :
09
b0 4
b0 7
0*
0-
00
b0 '
03
0)
0,
0/
02
05
08
0;
b0 #
b0 %
#1370
1!
16
b11 &
b11 :
19
b11 4
b11 7
1*
1-
10
b1111 '
13
1)
1,
1/
12
b1 #
b1 %
#1380
0!
06
b0 &
b0 :
09
b0 4
b0 7
0*
0-
00
b0 '
03
0)
0,
0/
02
15
18
b10 #
b10 %
#1390
1!
16
b11 &
b11 :
19
b11 4
b11 7
1*
1-
10
b1111 '
13
1)
1,
1/
12
b11 #
b11 %
#1400
0!
06
b0 &
b0 :
09
b0 4
b0 7
0*
0-
00
b0 '
03
0)
0,
0/
02
05
08
1;
b100 #
b100 %
#1410
1!
16
b11 &
b11 :
19
b11 4
b11 7
1*
1-
10
b1111 '
13
1)
1,
1/
12
b101 #
b101 %
#1420
0!
06
b0 &
b0 :
09
b0 4
b0 7
0*
0-
00
b0 '
03
0)
0,
0/
02
15
18
b110 #
b110 %
#1430
1!
16
b11 &
b11 :
19
b11 4
b11 7
1*
1-
10
b1111 '
13
1)
1,
1/
12
b111 #
b111 %
#1440
0!
06
b0 &
b0 :
09
b0 4
b0 7
0*
0-
00
b0 '
03
0)
0,
0/
02
05
08
0;
b0 #
b0 %
#1450
1!
16
b11 &
b11 :
19
b11 4
b11 7
1*
1-
10
b1111 '
13
1)
1,
1/
12
b1 #
b1 %
#1460
0!
06
b0 &
b0 :
09
b0 4
b0 7
0*
0-
00
b0 '
03
0)
0,
0/
02
15
18
b10 #
b10 %
#1470
1!
16
b11 &
b11 :
19
b11 4
b11 7
1*
1-
10
b1111 '
13
1)
1,
1/
12
b11 #
b11 %
#1480
0!
06
b0 &
b0 :
09
b0 4
b0 7
0*
0-
00
b0 '
03
0)
0,
0/
02
05
08
1;
b100 #
b100 %
#1490
1!
16
b11 &
b11 :
19
b11 4
b11 7
1*
1-
10
b1111 '
13
1)
1,
1/
12
b101 #
b101 %
#1500
0!
06
b0 &
b0 :
09
b0 4
b0 7
0*
0-
00
b0 '
03
0)
0,
0/
02
15
18
b110 #
b110 %
#1510
1!
16
b11 &
b11 :
19
b11 4
b11 7
1*
1-
10
b1111 '
13
1)
1,
1/
12
b111 #
b111 %
#1520
0!
06
b0 &
b0 :
09
b0 4
b0 7
0*
0-
00
b0 '
03
0)
0,
0/
02
05
08
0;
b0 #
b0 %
#1530
1!
16
b11 &
b11 :
19
b11 4
b11 7
1*
1-
10
b1111 '
13
1)
1,
1/
12
b1 #
b1 %
#1540
0!
06
b0 &
b0 :
09
b0 4
b0 7
0*
0-
00
b0 '
03
0)
0,
0/
02
15
18
b10 #
b10 %
#1550
1!
16
b11 &
b11 :
19
b11 4
b11 7
1*
1-
10
b1111 '
13
1)
1,
1/
12
b11 #
b11 %
#1560
0!
06
b0 &
b0 :
09
b0 4
b0 7
0*
0-
00
b0 '
03
0)
0,
0/
02
05
08
1;
b100 #
b100 %
#1570
1!
16
b11 &
b11 :
19
b11 4
b11 7
1*
1-
10
b1111 '
13
1)
1,
1/
12
b101 #
b101 %
#1580
0!
06
b0 &
b0 :
09
b0 4
b0 7
0*
0-
00
b0 '
03
0)
0,
0/
02
15
18
b110 #
b110 %
#1590
1!
16
b11 &
b11 :
19
b11 4
b11 7
1*
1-
10
b1111 '
13
1)
1,
1/
12
b111 #
b111 %
#1600
0!
06
b0 &
b0 :
09
b0 4
b0 7
0*
0-
00
b0 '
03
0)
0,
0/
02
05
08
0;
b0 #
b0 %
#1610
1!
16
b11 &
b11 :
19
b11 4
b11 7
1*
1-
10
b1111 '
13
1)
1,
1/
12
b1 #
b1 %
#1620
0!
06
b0 &
b0 :
09
b0 4
b0 7
0*
0-
00
b0 '
03
0)
0,
0/
02
15
18
b10 #
b10 %
#1630
1!
16
b11 &
b11 :
19
b11 4
b11 7
1*
1-
10
b1111 '
13
1)
1,
1/
12
b11 #
b11 %
#1640
0!
06
b0 &
b0 :
09
b0 4
b0 7
0*
0-
00
b0 '
03
0)
0,
0/
02
05
08
1;
b100 #
b100 %
#1650
1!
16
b11 &
b11 :
19
b11 4
b11 7
1*
1-
10
b1111 '
13
1)
1,
1/
12
b101 #
b101 %
#1660
0!
06
b0 &
b0 :
09
b0 4
b0 7
0*
0-
00
b0 '
03
0)
0,
0/
02
15
18
b110 #
b110 %
#1670
1!
16
b11 &
b11 :
19
b11 4
b11 7
1*
1-
10
b1111 '
13
1)
1,
1/
12
b111 #
b111 %
#1680
0!
06
b0 &
b0 :
09
b0 4
b0 7
0*
0-
00
b0 '
03
0)
0,
0/
02
05
08
0;
b0 #
b0 %
#1690
1!
16
b11 &
b11 :
19
b11 4
b11 7
1*
1-
10
b1111 '
13
1)
1,
1/
12
b1 #
b1 %
#1700
0!
06
b0 &
b0 :
09
b0 4
b0 7
0*
0-
00
b0 '
03
0)
0,
0/
02
15
18
b10 #
b10 %
#1710
1!
16
b11 &
b11 :
19
b11 4
b11 7
1*
1-
10
b1111 '
13
1)
1,
1/
12
b11 #
b11 %
#1720
0!
06
b0 &
b0 :
09
b0 4
b0 7
0*
0-
00
b0 '
03
0)
0,
0/
02
05
08
1;
b100 #
b100 %
#1730
1!
16
b11 &
b11 :
19
b11 4
b11 7
1*
1-
10
b1111 '
13
1)
1,
1/
12
b101 #
b101 %
#1740
0!
06
b0 &
b0 :
09
b0 4
b0 7
0*
0-
00
b0 '
03
0)
0,
0/
02
15
18
b110 #
b110 %
#1750
1!
16
b11 &
b11 :
19
b11 4
b11 7
1*
1-
10
b1111 '
13
1)
1,
1/
12
b111 #
b111 %
#1760
0!
06
b0 &
b0 :
09
b0 4
b0 7
0*
0-
00
b0 '
03
0)
0,
0/
02
05
08
0;
b0 #
b0 %
#1770
1!
16
b11 &
b11 :
19
b11 4
b11 7
1*
1-
10
b1111 '
13
1)
1,
1/
12
b1 #
b1 %
#1780
0!
06
b0 &
b0 :
09
b0 4
b0 7
0*
0-
00
b0 '
03
0)
0,
0/
02
15
18
b10 #
b10 %
#1790
1!
16
b11 &
b11 :
19
b11 4
b11 7
1*
1-
10
b1111 '
13
1)
1,
1/
12
b11 #
b11 %
#1800
0!
06
b0 &
b0 :
09
b0 4
b0 7
0*
0-
00
b0 '
03
0)
0,
0/
02
05
08
1;
b100 #
b100 %
#1810
1!
16
b11 &
b11 :
19
b11 4
b11 7
1*
1-
10
b1111 '
13
1)
1,
1/
12
b101 #
b101 %
#1820
0!
06
b0 &
b0 :
09
b0 4
b0 7
0*
0-
00
b0 '
03
0)
0,
0/
02
15
18
b110 #
b110 %
#1830
1!
16
b11 &
b11 :
19
b11 4
b11 7
1*
1-
10
b1111 '
13
1)
1,
1/
12
b111 #
b111 %
#1840
0!
06
b0 &
b0 :
09
b0 4
b0 7
0*
0-
00
b0 '
03
0)
0,
0/
02
05
08
0;
b0 #
b0 %
#1850
1!
16
b11 &
b11 :
19
b11 4
b11 7
1*
1-
10
b1111 '
13
1)
1,
1/
12
b1 #
b1 %
#1860
0!
06
b0 &
b0 :
09
b0 4
b0 7
0*
0-
00
b0 '
03
0)
0,
0/
02
15
18
b10 #
b10 %
#1870
1!
16
b11 &
b11 :
19
b11 4
b11 7
1*
1-
10
b1111 '
13
1)
1,
1/
12
b11 #
b11 %
#1880
0!
06
b0 &
b0 :
09
b0 4
b0 7
0*
0-
00
b0 '
03
0)
0,
0/
02
05
08
1;
b100 #
b100 %
#1890
1!
16
b11 &
b11 :
19
b11 4
b11 7
1*
1-
10
b1111 '
13
1)
1,
1/
12
b101 #
b101 %
#1900
0!
06
b0 &
b0 :
09
b0 4
b0 7
0*
0-
00
b0 '
03
0)
0,
0/
02
15
18
b110 #
b110 %
#1910
1!
16
b11 &
b11 :
19
b11 4
b11 7
1*
1-
10
b1111 '
13
1)
1,
1/
12
b111 #
b111 %
#1920
0!
06
b0 &
b0 :
09
b0 4
b0 7
0*
0-
00
b0 '
03
0)
0,
0/
02
05
08
0;
b0 #
b0 %
#1930
1!
16
b11 &
b11 :
19
b11 4
b11 7
1*
1-
10
b1111 '
13
1)
1,
1/
12
b1 #
b1 %
